helicopter/__init__.py
helicopter/config_private.py
helicopter/data.py
helicopter/feed.py
helicopter-0.0.6.dist-info/METADATA
helicopter-0.0.6.dist-info/WHEEL
helicopter-0.0.6.dist-info/entry_points.txt
helicopter-0.0.6.dist-info/top_level.txt
helicopter-0.0.6.dist-info/RECORD
