Metadata-Version: 2.1
Name: helicopter
Version: 0.0.6
Summary: Linking SciML Julia helicopter challenge to Microprediction.Org
Home-page: https://github.com/microprediction/helicopter
Author: microprediction
Author-email: info@microprediction.com
License: MIT
Platform: UNKNOWN
Classifier: License :: OSI Approved :: MIT License
Classifier: Programming Language :: Python :: 3
Classifier: Programming Language :: Python :: 3.7
Requires-Dist: numpy
Requires-Dist: pandas
Requires-Dist: pathlib
Requires-Dist: requests
Requires-Dist: microprediction (>=0.9.11)
Requires-Dist: copulas
Requires-Dist: matplotlib
